README.md
setup.py
commonlib/__init__.py
commonlib/caseFunction.py
commonlib/newdir.py
commonlib/sendEmail.py
commonlib/userFunction.py
lyh_ui_autotest.egg-info/PKG-INFO
lyh_ui_autotest.egg-info/SOURCES.txt
lyh_ui_autotest.egg-info/dependency_links.txt
lyh_ui_autotest.egg-info/top_level.txt
testcase/__init__.py
testdata/__init__.py
testdata/common.py