Metadata-Version: 2.1
Name: lyh-ui-autotest
Version: 0.0.1
Summary: lyh ui autoTest
Home-page: https://github.com/vissyzhu/lyhui.git
Author: vissyzhu
Author-email: 1209354095@qq.com
License: MIT
Platform: UNKNOWN
